{
  "version": "6.0",
  "nxVersion": "17.1.1",
  "deps": {
    "@angular/animations": "~17.0.0",
    "@angular/cdk": "^17.0.3",
    "@angular/common": "~17.0.0",
    "@angular/compiler": "~17.0.0",
    "@angular/core": "~17.0.0",
    "@angular/fire": "17.0.1",
    "@angular/forms": "~17.0.0",
    "@angular/material": "^17.0.3",
    "@angular/platform-browser": "~17.0.0",
    "@angular/platform-browser-dynamic": "~17.0.0",
    "@angular/platform-server": "~17.0.0",
    "@angular/router": "~17.0.0",
    "@angular/ssr": "~17.0.0",
    "@angular/youtube-player": "^17.0.0",
    "@ngneat/transloco": "^6.0.0",
    "@ngneat/transloco-scoped-libs": "^5.0.3",
    "@ngrx/signals": "^17.1.1",
    "@nx/angular": "17.2.0",
    "express": "~4.18.2",
    "immer": "^10.0.3",
    "rxjs": "~7.8.1",
    "tslib": "^2.6.2",
    "zone.js": "0.14.2",
    "@angular-devkit/build-angular": "~17.0.0",
    "@angular-devkit/core": "~17.0.0",
    "@angular-devkit/schematics": "~17.0.0",
    "@angular-eslint/eslint-plugin": "~17.0.0",
    "@angular-eslint/eslint-plugin-template": "~17.0.0",
    "@angular-eslint/template-parser": "~17.0.0",
    "@angular/cli": "~17.0.0",
    "@angular/compiler-cli": "~17.0.0",
    "@angular/language-service": "~17.0.0",
    "@nx/eslint": "17.2.0",
    "@nx/eslint-plugin": "17.2.0",
    "@nx/jest": "17.2.0",
    "@nx/js": "17.2.0",
    "@nx/linter": "17.1.1",
    "@nx/workspace": "17.2.0",
    "@schematics/angular": "~17.0.0",
    "@swc-node/register": "~1.6.7",
    "@swc/core": "~1.3.85",
    "@types/express": "4.17.14",
    "@types/jest": "^29.4.0",
    "@types/node": "18.16.9",
    "@typescript-eslint/eslint-plugin": "^6.9.1",
    "@typescript-eslint/parser": "^6.9.1",
    "eslint": "~8.48.0",
    "eslint-config-prettier": "^9.0.0",
    "jest": "^29.7.0",
    "jest-environment-jsdom": "^29.7.0",
    "jest-preset-angular": "13.1.4",
    "jsonc-eslint-parser": "^2.4.0",
    "ng-packagr": "17.0.0",
    "nx": "17.1.1",
    "postcss": "^8.4.31",
    "postcss-import": "~15.1.0",
    "postcss-preset-env": "~9.3.0",
    "postcss-url": "~10.1.3",
    "prettier": "^3.0.3",
    "ts-jest": "^29.1.1",
    "ts-node": "10.9.1",
    "typescript": "~5.2.2"
  },
  "pathMappings": {
    "@axim-anahnu/common/environment": [
      "libs/common/environment/index.ts"
    ],
    "@axim-anahnu/common/signal-store-features": [
      "libs/common/signal-store-features/index.ts"
    ],
    "@axim-anahnu/common/transloco": [
      "libs/common/transloco/index.ts"
    ],
    "@axim-anahnu/content/content": [
      "libs/content/content/index.ts"
    ],
    "@axim-anahnu/content/description": [
      "libs/content/description/index.ts"
    ],
    "@axim-anahnu/content/history": [
      "libs/content/history/index.ts"
    ],
    "@axim-anahnu/content/source": [
      "libs/content/source/index.ts"
    ]
  },
  "nxJsonPlugins": [],
  "fileMap": {
    "nonProjectFiles": [
      {
        "file": ".editorconfig",
        "hash": "11532813898455409296"
      },
      {
        "file": ".eslintignore",
        "hash": "13404745306227114823"
      },
      {
        "file": ".eslintrc.json",
        "hash": "4566917484430375526"
      },
      {
        "file": ".firebaserc",
        "hash": "12631551413043340450"
      },
      {
        "file": ".gitignore",
        "hash": "11424774732679295364"
      },
      {
        "file": ".nx/cache/d/daemon.log",
        "hash": "10316051563629707397"
      },
      {
        "file": ".nx/cache/d/server-process.json",
        "hash": "10089868760581392602"
      },
      {
        "file": ".nx/cache/file-map.json",
        "hash": "10112744463209054131"
      },
      {
        "file": ".nx/cache/lockfile.hash",
        "hash": "17077403397737737166"
      },
      {
        "file": ".nx/cache/parsed-lock-file.json",
        "hash": "4588238836681311643"
      },
      {
        "file": ".nx/cache/project-graph.json",
        "hash": "9837801295190120990"
      },
      {
        "file": ".nx/cache/project-graph.json~3369a8f3",
        "hash": "1766886065394869799"
      },
      {
        "file": ".nx/cache/project-graph.json~b72b2fd6",
        "hash": "2075223547591592795"
      },
      {
        "file": ".nx/cache/terminalOutputs/10943186080468331968",
        "hash": "2216077504538259826"
      },
      {
        "file": ".nx/cache/terminalOutputs/11929401256528672157",
        "hash": "8780548503949569162"
      },
      {
        "file": ".nx/cache/terminalOutputs/12562897203935929758",
        "hash": "1213505390264125551"
      },
      {
        "file": ".nx/cache/terminalOutputs/15279794573928987144",
        "hash": "10452783003116897598"
      },
      {
        "file": ".nx/cache/terminalOutputs/16613964315802740261",
        "hash": "5183336937004237768"
      },
      {
        "file": ".nx/cache/terminalOutputs/4096000018378225076",
        "hash": "5844584799492820200"
      },
      {
        "file": ".nx/cache/terminalOutputs/4287666463998004236",
        "hash": "12236839090656936542"
      },
      {
        "file": ".nx/cache/terminalOutputs/4835848754066100499",
        "hash": "747765318700908277"
      },
      {
        "file": ".nx/cache/terminalOutputs/8831342289853139919",
        "hash": "10040886381975309572"
      },
      {
        "file": ".nx/cache/terminalOutputs/9094362455176039668",
        "hash": "12879037991440336172"
      },
      {
        "file": ".prettierignore",
        "hash": "5519981940544710039"
      },
      {
        "file": ".prettierrc",
        "hash": "6820402234827505055"
      },
      {
        "file": ".vscode/extensions.json",
        "hash": "13391140343975966684"
      },
      {
        "file": "README.md",
        "hash": "7071106593202347880"
      },
      {
        "file": "firebase.json",
        "hash": "11367074832724451337"
      },
      {
        "file": "i18n/en.json",
        "hash": "12166922465874784511"
      },
      {
        "file": "i18n/he.json",
        "hash": "10619627341681427594"
      },
      {
        "file": "images/flag-1.jpeg",
        "hash": "18124406720871520388"
      },
      {
        "file": "jest.config.ts",
        "hash": "3407785570333453138"
      },
      {
        "file": "jest.preset.js",
        "hash": "7473220183190921152"
      },
      {
        "file": "migrations.json",
        "hash": "14419208328759862936"
      },
      {
        "file": "nx.json",
        "hash": "2127356856071307666"
      },
      {
        "file": "package-lock.json",
        "hash": "16331171781480243724"
      },
      {
        "file": "package.json",
        "hash": "13167014678810094474"
      },
      {
        "file": "styles/palette.scss",
        "hash": "16962711571783898380"
      },
      {
        "file": "styles/styles.scss",
        "hash": "9391843718206367770"
      },
      {
        "file": "styles/variables.scss",
        "hash": "10837310790155904642"
      },
      {
        "file": "transloco.config.js",
        "hash": "3668099396342507452"
      },
      {
        "file": "tsconfig.base.json",
        "hash": "14953385041058893874"
      }
    ],
    "projectFileMap": {
      "main": [
        {
          "file": "apps/main/.eslintrc.json",
          "hash": "10024625287610618267"
        },
        {
          "file": "apps/main/jest.config.ts",
          "hash": "10102445100471367535"
        },
        {
          "file": "apps/main/project.json",
          "hash": "15117094518865420834"
        },
        {
          "file": "apps/main/server.ts",
          "hash": "15053072606401062197",
          "deps": [
            "npm:zone.js",
            "npm:@angular/common",
            "npm:@nguniversal/express-engine",
            "npm:express",
            "npm:node:fs",
            "npm:node:path"
          ]
        },
        {
          "file": "apps/main/src/app/app.component.spec.ts",
          "hash": "1263815157723373484",
          "deps": [
            "npm:@angular/core",
            "npm:@angular/router"
          ]
        },
        {
          "file": "apps/main/src/app/app.component.ts",
          "hash": "8383627837315570658",
          "deps": [
            "npm:@angular/core",
            "npm:@angular/material",
            "npm:@angular/router"
          ]
        },
        {
          "file": "apps/main/src/app/app.config.server.ts",
          "hash": "15184490126418035619",
          "deps": [
            "npm:@angular/core",
            "npm:@angular/platform-server"
          ]
        },
        {
          "file": "apps/main/src/app/app.config.ts",
          "hash": "10787730106450131115",
          "deps": [
            "npm:@angular/common",
            "npm:@angular/core",
            "npm:@angular/platform-browser",
            "npm:@angular/router",
            "common",
            "npm:@angular/fire"
          ]
        },
        {
          "file": "apps/main/src/app/app.routes.ts",
          "hash": "18227141760750256770",
          "deps": [
            "npm:@angular/core",
            "npm:@angular/router",
            "common",
            [
              "content",
              "dynamic"
            ]
          ]
        },
        {
          "file": "apps/main/src/app/transloco-loader.ts",
          "hash": "2486619763921365912",
          "deps": [
            "npm:@angular/common",
            "npm:@angular/core",
            "common",
            "npm:@ngneat/transloco"
          ]
        },
        {
          "file": "apps/main/src/assets/.gitkeep",
          "hash": "3244421341483603138"
        },
        {
          "file": "apps/main/src/environments/environment.development.ts",
          "hash": "14398588251721517625"
        },
        {
          "file": "apps/main/src/environments/environment.firebase.ts",
          "hash": "12995033551687412200"
        },
        {
          "file": "apps/main/src/environments/environment.ts",
          "hash": "7065959230643633587"
        },
        {
          "file": "apps/main/src/favicon.ico",
          "hash": "9303420814833116677"
        },
        {
          "file": "apps/main/src/index.html",
          "hash": "10886212974788817154"
        },
        {
          "file": "apps/main/src/main.server.ts",
          "hash": "9257623809215978365",
          "deps": [
            "npm:@angular/platform-browser"
          ]
        },
        {
          "file": "apps/main/src/main.ts",
          "hash": "875041330523952236",
          "deps": [
            "npm:@angular/platform-browser"
          ]
        },
        {
          "file": "apps/main/src/test-setup.ts",
          "hash": "10765977267162271731",
          "deps": [
            "npm:jest-preset-angular"
          ]
        },
        {
          "file": "apps/main/tsconfig.app.json",
          "hash": "15840844869456775012"
        },
        {
          "file": "apps/main/tsconfig.editor.json",
          "hash": "6816855480324741077"
        },
        {
          "file": "apps/main/tsconfig.json",
          "hash": "17021277375021554599"
        },
        {
          "file": "apps/main/tsconfig.server.json",
          "hash": "16829546870058365246"
        },
        {
          "file": "apps/main/tsconfig.spec.json",
          "hash": "1930986853382524452"
        }
      ],
      "content": [
        {
          "file": "libs/content/.eslintrc.json",
          "hash": "14297704538809278712"
        },
        {
          "file": "libs/content/README.md",
          "hash": "8492751482962435461"
        },
        {
          "file": "libs/content/content/components/content/content.component.spec.ts",
          "hash": "10173717789979184764",
          "deps": [
            "npm:@angular/core"
          ]
        },
        {
          "file": "libs/content/content/components/content/content.component.ts",
          "hash": "16807461563159576830",
          "deps": [
            "npm:@angular/core",
            "npm:@angular/material",
            "npm:@ngneat/transloco"
          ]
        },
        {
          "file": "libs/content/content/content.routes.ts",
          "hash": "9924837618323677060",
          "deps": [
            "npm:@angular/router"
          ]
        },
        {
          "file": "libs/content/content/index.ts",
          "hash": "2656568455426674007"
        },
        {
          "file": "libs/content/content/ng-package.json",
          "hash": "9603264685267935717"
        },
        {
          "file": "libs/content/description/README.md",
          "hash": "11310932657820911766"
        },
        {
          "file": "libs/content/description/components/description/description.component.scss",
          "hash": "9627247491737658813"
        },
        {
          "file": "libs/content/description/components/description/description.component.spec.ts",
          "hash": "10108950466680488632",
          "deps": [
            "npm:@angular/core"
          ]
        },
        {
          "file": "libs/content/description/components/description/description.component.ts",
          "hash": "13028462759062505",
          "deps": [
            "npm:@angular/core",
            "npm:@ngneat/transloco"
          ]
        },
        {
          "file": "libs/content/description/index.ts",
          "hash": "9753054215237253349"
        },
        {
          "file": "libs/content/description/ng-package.json",
          "hash": "9603264685267935717"
        },
        {
          "file": "libs/content/history/README.md",
          "hash": "18044778919883329556"
        },
        {
          "file": "libs/content/history/components/history/history.component.spec.ts",
          "hash": "3071729820294124037",
          "deps": [
            "npm:@angular/core"
          ]
        },
        {
          "file": "libs/content/history/components/history/history.component.ts",
          "hash": "12817386571217814467",
          "deps": [
            "npm:@angular/core",
            "npm:@angular/common",
            "npm:@angular/material"
          ]
        },
        {
          "file": "libs/content/history/components/holocaust/holocaust.component.spec.ts",
          "hash": "16625639526603957314",
          "deps": [
            "npm:@angular/core"
          ]
        },
        {
          "file": "libs/content/history/components/holocaust/holocaust.component.ts",
          "hash": "14854257812435815005",
          "deps": [
            "npm:@angular/core",
            "npm:@angular/common"
          ]
        },
        {
          "file": "libs/content/history/components/second-house-destruction/second-house-destruction.component.spec.ts",
          "hash": "7828998721018581814",
          "deps": [
            "npm:@angular/core"
          ]
        },
        {
          "file": "libs/content/history/components/second-house-destruction/second-house-destruction.component.ts",
          "hash": "9944060097259232740",
          "deps": [
            "npm:@angular/core",
            "npm:@angular/common"
          ]
        },
        {
          "file": "libs/content/history/index.ts",
          "hash": "10364919303807209930"
        },
        {
          "file": "libs/content/history/ng-package.json",
          "hash": "9603264685267935717"
        },
        {
          "file": "libs/content/i18n/en.json",
          "hash": "12166922465874784511"
        },
        {
          "file": "libs/content/i18n/he.json",
          "hash": "14268245456358719113"
        },
        {
          "file": "libs/content/index.ts",
          "hash": "3366108681024234455"
        },
        {
          "file": "libs/content/jest.config.ts",
          "hash": "3067134394015281324"
        },
        {
          "file": "libs/content/ng-package.json",
          "hash": "952438439689789199"
        },
        {
          "file": "libs/content/package.json",
          "hash": "13040296260414484764",
          "deps": [
            "npm:tslib",
            "npm:@angular/common",
            "npm:@angular/core"
          ]
        },
        {
          "file": "libs/content/project.json",
          "hash": "193663478173008809"
        },
        {
          "file": "libs/content/source/README.md",
          "hash": "11604957381876317337"
        },
        {
          "file": "libs/content/source/components/source/source.component.spec.ts",
          "hash": "12620433757899815014",
          "deps": [
            "npm:@angular/core"
          ]
        },
        {
          "file": "libs/content/source/components/source/source.component.ts",
          "hash": "7421301584020060755",
          "deps": [
            "npm:@angular/core",
            "npm:@angular/youtube-player"
          ]
        },
        {
          "file": "libs/content/source/components/youtube-item/youtube-item.component.scss",
          "hash": "10073400031118858514"
        },
        {
          "file": "libs/content/source/components/youtube-item/youtube-item.component.spec.ts",
          "hash": "16857624107846252663",
          "deps": [
            "npm:@angular/core"
          ]
        },
        {
          "file": "libs/content/source/components/youtube-item/youtube-item.component.ts",
          "hash": "11340961966398099144",
          "deps": [
            "npm:@angular/core",
            "npm:@angular/youtube-player",
            "npm:@angular/common"
          ]
        },
        {
          "file": "libs/content/source/index.ts",
          "hash": "18325968995626243987"
        },
        {
          "file": "libs/content/source/models/youtube-source.model.ts",
          "hash": "5274587496977748243"
        },
        {
          "file": "libs/content/source/ng-package.json",
          "hash": "9603264685267935717"
        },
        {
          "file": "libs/content/source/service/youtube-source/youtube-source.service.spec.ts",
          "hash": "9704365995731581554",
          "deps": [
            "npm:@angular/core"
          ]
        },
        {
          "file": "libs/content/source/service/youtube-source/youtube-source.service.ts",
          "hash": "17973738581275405532",
          "deps": [
            "npm:@angular/core",
            "npm:@angular/fire",
            "npm:rxjs"
          ]
        },
        {
          "file": "libs/content/source/service/youtube-source-store/youtube-source-store.service.spec.ts",
          "hash": "2012511178998263033",
          "deps": [
            "npm:@angular/core"
          ]
        },
        {
          "file": "libs/content/source/service/youtube-source-store/youtube-source-store.service.ts",
          "hash": "4034840700240367701",
          "deps": [
            "npm:@angular/core",
            "npm:rxjs",
            "npm:@ngrx/signals",
            "common"
          ]
        },
        {
          "file": "libs/content/test-setup.ts",
          "hash": "10765977267162271731",
          "deps": [
            "npm:jest-preset-angular"
          ]
        },
        {
          "file": "libs/content/tsconfig.json",
          "hash": "7184861466157324158"
        },
        {
          "file": "libs/content/tsconfig.lib.json",
          "hash": "10237209988492787423"
        },
        {
          "file": "libs/content/tsconfig.lib.prod.json",
          "hash": "16219944552368449858"
        },
        {
          "file": "libs/content/tsconfig.spec.json",
          "hash": "552591673985527526"
        }
      ],
      "common": [
        {
          "file": "libs/common/.eslintrc.json",
          "hash": "7696856466819168935"
        },
        {
          "file": "libs/common/README.md",
          "hash": "5067725685752823321"
        },
        {
          "file": "libs/common/environment/README.md",
          "hash": "15668142700699082589"
        },
        {
          "file": "libs/common/environment/index.ts",
          "hash": "5946309871401332774"
        },
        {
          "file": "libs/common/environment/models/environment.model.ts",
          "hash": "13237531130872038029"
        },
        {
          "file": "libs/common/environment/ng-package.json",
          "hash": "9603264685267935717"
        },
        {
          "file": "libs/common/environment/tokens/environment.token.ts",
          "hash": "13030752035856261970",
          "deps": [
            "npm:@angular/core"
          ]
        },
        {
          "file": "libs/common/index.ts",
          "hash": "17425740688393819411"
        },
        {
          "file": "libs/common/jest.config.ts",
          "hash": "10662020793002465443"
        },
        {
          "file": "libs/common/ng-package.json",
          "hash": "18314343692498525505"
        },
        {
          "file": "libs/common/package.json",
          "hash": "4333027986978267130",
          "deps": [
            "npm:tslib",
            "npm:@angular/common",
            "npm:@angular/core"
          ]
        },
        {
          "file": "libs/common/project.json",
          "hash": "5414647401163871086"
        },
        {
          "file": "libs/common/signal-store-features/call-state.feature.ts",
          "hash": "3603150016251108211",
          "deps": [
            "npm:@angular/core",
            "npm:@angular/common",
            "npm:@ngrx/signals"
          ]
        },
        {
          "file": "libs/common/signal-store-features/index.ts",
          "hash": "17768025364673105900"
        },
        {
          "file": "libs/common/signal-store-features/ng-package.json",
          "hash": "9603264685267935717"
        },
        {
          "file": "libs/common/test-setup.ts",
          "hash": "10765977267162271731",
          "deps": [
            "npm:jest-preset-angular"
          ]
        },
        {
          "file": "libs/common/transloco/README.md",
          "hash": "6231963431679707068"
        },
        {
          "file": "libs/common/transloco/index.ts",
          "hash": "13148200914922504984"
        },
        {
          "file": "libs/common/transloco/injection-tokens/direction-map.token.ts",
          "hash": "15731443920800245207",
          "deps": [
            "npm:@angular/core"
          ]
        },
        {
          "file": "libs/common/transloco/injection-tokens/language-url.token.ts",
          "hash": "13510813602379433143",
          "deps": [
            "npm:@angular/core"
          ]
        },
        {
          "file": "libs/common/transloco/injection-tokens/transloco-settings.token.ts",
          "hash": "15303879212762064426",
          "deps": [
            "npm:@angular/core"
          ]
        },
        {
          "file": "libs/common/transloco/models/direction.type.ts",
          "hash": "13506328187052182494"
        },
        {
          "file": "libs/common/transloco/models/transoloco-settings.model.ts",
          "hash": "15617781629270877745"
        },
        {
          "file": "libs/common/transloco/ng-package.json",
          "hash": "9603264685267935717"
        },
        {
          "file": "libs/common/transloco/providers/transloco.provider.ts",
          "hash": "9781402699909956850",
          "deps": [
            "npm:@angular/core",
            "npm:@ngneat/transloco"
          ]
        },
        {
          "file": "libs/common/transloco/services/transloco-attributes/transloco-attributes.service.spec.ts",
          "hash": "17590999863412699613",
          "deps": [
            "npm:@angular/core"
          ]
        },
        {
          "file": "libs/common/transloco/services/transloco-attributes/transloco-attributes.service.ts",
          "hash": "525189681013535877",
          "deps": [
            "npm:@angular/common",
            "npm:@angular/core",
            "npm:@ngneat/transloco"
          ]
        },
        {
          "file": "libs/common/transloco/services/transloco-loader/transloco-loader.service.ts",
          "hash": "3461281908203654675",
          "deps": [
            "npm:@angular/common",
            "npm:@angular/core",
            "npm:@ngneat/transloco"
          ]
        },
        {
          "file": "libs/common/tsconfig.json",
          "hash": "7184861466157324158"
        },
        {
          "file": "libs/common/tsconfig.lib.json",
          "hash": "10237209988492787423"
        },
        {
          "file": "libs/common/tsconfig.lib.prod.json",
          "hash": "16219944552368449858"
        },
        {
          "file": "libs/common/tsconfig.spec.json",
          "hash": "552591673985527526"
        }
      ]
    }
  }
}
